pyphonetics/__init__.py
pyphonetics/exceptions.py
pyphonetics/utils.py
pyphonetics/distance_metrics/__init__.py
pyphonetics/distance_metrics/hamming.py
pyphonetics/distance_metrics/levenshtein.py
pyphonetics/phonetics/__init__.py
pyphonetics/phonetics/fuzzy_soundex.py
pyphonetics/phonetics/lein.py
pyphonetics/phonetics/metaphone.py
pyphonetics/phonetics/mra.py
pyphonetics/phonetics/phonetic_algorithm.py
pyphonetics/phonetics/refined_soundex.py
pyphonetics/phonetics/soundex.py
pyphonetics-0.5.3.dist-info/LICENSE.rst
pyphonetics-0.5.3.dist-info/WHEEL
pyphonetics-0.5.3.dist-info/METADATA
pyphonetics-0.5.3.dist-info/RECORD
