Metadata-Version: 1.1
Name: pyphonetics
Version: 0.5.3
Summary: A Python 3 phonetics library.
Home-page: https://github.com/Lilykos/pyphonetics
Author: Lilykos
Author-email: ilias.koutsakis@gmail.com
